zyte_spider_templates/__init__.py
zyte_spider_templates/_geolocations.py
zyte_spider_templates/_lang_codes.py
zyte_spider_templates/documentation.py
zyte_spider_templates/heuristics.py
zyte_spider_templates/middlewares.py
zyte_spider_templates/params.py
zyte_spider_templates/utils.py
zyte_spider_templates/page_objects/__init__.py
zyte_spider_templates/page_objects/product_navigation_heuristics.py
zyte_spider_templates/pages/__init__.py
zyte_spider_templates/pages/product_navigation_heuristics.py
zyte_spider_templates/spiders/__init__.py
zyte_spider_templates/spiders/_google_domains.py
zyte_spider_templates/spiders/base.py
zyte_spider_templates/spiders/ecommerce.py
zyte_spider_templates/spiders/ecommerce_navigation.py
zyte_spider_templates/spiders/serp.py
zyte_spider_templates_enhanced-0.0.8.dist-info/licenses/LICENSE
zyte_spider_templates_enhanced-0.0.8.dist-info/METADATA
zyte_spider_templates_enhanced-0.0.8.dist-info/WHEEL
zyte_spider_templates_enhanced-0.0.8.dist-info/top_level.txt
zyte_spider_templates_enhanced-0.0.8.dist-info/RECORD
