Metadata-Version: 2.4
Name: zyte-spider-templates-enhanced
Version: 0.0.8
Home-page: https://github.com/felipdc/zyte-spider-templates
License-File: LICENSE
Requires-Dist: pydantic>=2.1
Requires-Dist: requests>=0.10.1
Requires-Dist: scrapy>=2.11.0
Requires-Dist: scrapy-poet>=0.24.0
Requires-Dist: scrapy-spider-metadata>=0.2.0
Requires-Dist: scrapy-zyte-api[provider]>=0.23.0
Requires-Dist: zyte-common-items>=0.23.0
Dynamic: home-page
Dynamic: license-file
Dynamic: requires-dist
